carbonarc/__init__.py
carbonarc/base.py
carbonarc/client.py
carbonarc/data.py
carbonarc/explorer.py
carbonarc/hub.py
carbonarc/ontology.py
carbonarc/utils/__init__.py
carbonarc/utils/auth.py
carbonarc/utils/client.py
carbonarc/utils/exceptions.py
carbonarc/utils/manager.py
carbonarc/utils/timeseries.py
carbonarc_cli/__init__.py
carbonarc_cli/cli.py
carbonarc-1.1.8.dist-info/METADATA
carbonarc-1.1.8.dist-info/WHEEL
carbonarc-1.1.8.dist-info/entry_points.txt
carbonarc-1.1.8.dist-info/licenses/LICENSE
carbonarc-1.1.8.dist-info/RECORD
